ateto/__init__.py
ateto/cli.py
ateto/conf.py
ateto/data.py
ateto/medias.py
ateto/models.py
ateto/sync.py
ateto/templates.py
ateto/utils.py
ateto/watcher.py
ateto-0.2.1.dist-info/METADATA
ateto-0.2.1.dist-info/WHEEL
ateto-0.2.1.dist-info/entry_points.txt
ateto-0.2.1.dist-info/RECORD
