Metadata-Version: 2.1
Name: ateto
Version: 0.2.1
Summary: This is a set of tools to write templates outside of Anki.
Home-page: https://codeberg.org/bisam/ateto
Keywords: anki,templates
Author: bisam
Author-email: bisam@r4.re
Requires-Python: >=3.10,<4.0
Classifier: Programming Language :: Python :: 3
Classifier: Programming Language :: Python :: 3.10
Classifier: Programming Language :: Python :: 3.11
Requires-Dist: Jinja2 (>=3.1,<4.0)
Requires-Dist: beautifulsoup4 (>=4.1,<5.0)
Requires-Dist: click (>=8.1,<9.0)
Requires-Dist: pyyaml (>=6.0,<7.0)
Requires-Dist: requests (>=2.28,<3.0)
Requires-Dist: watchdog (>=2.2,<3.0)
Requires-Dist: xdg (>=5.1,<6.0)
Project-URL: Repository, https://codeberg.org/bisam/ateto
